.gitignore
LICENSE
MANIFEST.in
README.md
pyproject.toml
setup.cfg
setup.py
_mining/README.md
_mining/make_channels.py
_mining/make_double_moments.py
_mining/make_parfile.py
_mining/make_single_moments.py
_mining/plot_attributes_model.py
_mining/plot_azimuthal_profiles.py
_mining/plot_channel+peakint.py
_mining/plot_channel+residuals.py
_mining/plot_gradient.py
_mining/plot_lineprofiles.py
_mining/plot_moment+3d.py
_mining/plot_moment+comparison.py
_mining/plot_moment+offset.py
_mining/plot_moment+residuals.py
_mining/plot_peak_residuals.py
_mining/plot_radial_profiles.py
_mining/plot_residuals+all.py
_mining/plot_residuals+deproj.py
_mining/plot_residuals+filaments.py
_mining/plot_velocity_components.py
_mining/show_parcube.py
_mining/utils.py
discminer/__init__.py
discminer/_version.py
discminer/cart.py
discminer/constants.py
discminer/core.py
discminer/cube.py
discminer/dev_model.py
discminer/diff_interp.py
discminer/disc2d.py
discminer/grid.py
discminer/mining_control.py
discminer/mining_utils.py
discminer/model.py
discminer/pick.py
discminer/plottools.py
discminer/rail.py
discminer/testyapf.py
discminer/units.py
discminer.egg-info/PKG-INFO
discminer.egg-info/SOURCES.txt
discminer.egg-info/dependency_links.txt
discminer.egg-info/entry_points.txt
discminer.egg-info/requires.txt
discminer.egg-info/top_level.txt
discminer/icons/button_box.png
discminer/icons/button_cursor.jpeg
discminer/icons/button_path.png
discminer/icons/button_return.png
discminer/icons/button_surface.png
discminer/icons/button_trash.jpg
discminer/icons/logo.txt
discminer/mining/make_channels.py
discminer/mining/make_double_moments.py
discminer/mining/make_parfile.py
discminer/mining/make_prepare_data.py
discminer/mining/make_single_moments.py
discminer/mining/make_skewkurt_moments.py
discminer/mining/plot_attributes_model.py
discminer/mining/plot_azimuthal_profiles.py
discminer/mining/plot_channels+peakint.py
discminer/mining/plot_gradient.py
discminer/mining/plot_intensity_distribution.py
discminer/mining/plot_isovelocities.py
discminer/mining/plot_moment+offset.py
discminer/mining/plot_moment+residuals.py
discminer/mining/plot_peak_residuals.py
discminer/mining/plot_pv_diagram.py
