Metadata-Version: 2.1
Name: discminer
Version: 0.4.5
Summary: Python package for parametric modelling of intensity channel maps from gas discs
Home-page: https://github.com/andizq/discminer
Author: Andres F. Izquierdo
Author-email: andres.izquierdo.c@gmail.com
License: UNKNOWN
Project-URL: Bug Reports, https://github.com/andizq/discminer/issues
Project-URL: Source, https://github.com/andizq/discminer/
Keywords: astronomy,discs,disks,planets,detection
Platform: UNKNOWN
Classifier: Development Status :: 4 - Beta
Classifier: Topic :: Scientific/Engineering :: Astronomy
Classifier: License :: OSI Approved :: MIT License
Classifier: Programming Language :: Python :: 3 :: Only
Requires-Python: >=3.6, <4
